{
	"info": {
		"_postman_id": "017078f6-c6f9-4cc8-ad7e-80c8624c1f7a",
		"name": "Scaler_BE",
		"schema": "https://schema.getpostman.com/json/collection/v2.1.0/collection.json",
		"_exporter_id": "14999249",
		"_collection_link": "https://speeding-flare-651730.postman.co/workspace/Scaler~6daf33ba-ed66-4f3e-a6b6-313334a475f1/collection/14999249-017078f6-c6f9-4cc8-ad7e-80c8624c1f7a?action=share&source=collection_link&creator=14999249"
	},
	"item": [
		{
			"name": "authentication",
			"item": [
				{
					"name": "signup",
					"request": {
						"method": "POST",
						"header": [],
						"body": {
							"mode": "raw",
							"raw": "{\r\n    \"email\": \"contact2theshreya@gmail.com\",\r\n    \"password\": \"sherpauts\"\r\n}",
							"options": {
								"raw": {
									"language": "json"
								}
							}
						},
						"url": {
							"raw": "http://localhost:8080/auth/sign_up",
							"protocol": "http",
							"host": [
								"localhost"
							],
							"port": "8080",
							"path": [
								"auth",
								"sign_up"
							]
						}
					},
					"response": []
				},
				{
					"name": "login",
					"request": {
						"method": "POST",
						"header": [],
						"body": {
							"mode": "raw",
							"raw": "{\r\n    \"email\": \"contact2theshreya@gmail.com\",\r\n    \"password\": \"sherpauts\"\r\n}",
							"options": {
								"raw": {
									"language": "json"
								}
							}
						},
						"url": {
							"raw": "http://localhost:8080/auth/login",
							"protocol": "http",
							"host": [
								"localhost"
							],
							"port": "8080",
							"path": [
								"auth",
								"login"
							]
						}
					},
					"response": []
				},
				{
					"name": "validate",
					"protocolProfileBehavior": {
						"disableBodyPruning": true
					},
					"request": {
						"method": "GET",
						"header": [],
						"body": {
							"mode": "raw",
							"raw": "{\r\n    \"userId\": 1,\r\n    \"token\": \"eyJhbGciOiJIUzI1NiJ9.eyJ1c2VyX2lkIjoxLCJyb2xlcyI6W10sImVtYWlsIjoiY29udGFjdDJ0aGVzaHJleWFAZ21haWwuY29tIiwiZXhwIjoxNzM5ODA5MDY0LCJpYXQiOjE3MzcyMTcwNjR9.AmpMVf5mvBhBv5VXQj8zXK3oWJm33rP9fqmzcf926aA\"\r\n}",
							"options": {
								"raw": {
									"language": "json"
								}
							}
						},
						"url": {
							"raw": "http://localhost:8080/auth/validate",
							"protocol": "http",
							"host": [
								"localhost"
							],
							"port": "8080",
							"path": [
								"auth",
								"validate"
							]
						}
					},
					"response": []
				}
			]
		},
		{
			"name": "oauth",
			"item": [
				{
					"name": "oauth-login and fetch product",
					"request": {
						"auth": {
							"type": "oauth2",
							"oauth2": [
								{
									"key": "tokenName",
									"value": "test3",
									"type": "string"
								},
								{
									"key": "scope",
									"value": "openid profile",
									"type": "string"
								},
								{
									"key": "clientSecret",
									"value": "productservicepassword",
									"type": "string"
								},
								{
									"key": "accessTokenUrl",
									"value": "http://localhost:8090/oauth2/token",
									"type": "string"
								},
								{
									"key": "authUrl",
									"value": "http://localhost:8090/oauth2/authorize",
									"type": "string"
								},
								{
									"key": "clientId",
									"value": "productservice",
									"type": "string"
								},
								{
									"key": "grant_type",
									"value": "authorization_code",
									"type": "string"
								},
								{
									"key": "addTokenTo",
									"value": "header",
									"type": "string"
								}
							]
						},
						"method": "GET",
						"header": [],
						"url": {
							"raw": "http://localhost:8080/products/1",
							"protocol": "http",
							"host": [
								"localhost"
							],
							"port": "8080",
							"path": [
								"products",
								"1"
							]
						}
					},
					"response": []
				}
			]
		},
		{
			"name": "craeteProduct",
			"request": {
				"method": "POST",
				"header": [],
				"body": {
					"mode": "raw",
					"raw": "{\r\n    \"id\": 5,\r\n    \"title\": \"t1\",\r\n    \"description\": \"t1\",\r\n    \"price\": 0.0123,\r\n    \"imageUrl\": \"url1\",\r\n    \"category\": \"peopele_new\",\r\n    \"deleted\": false\r\n}",
					"options": {
						"raw": {
							"language": "json"
						}
					}
				},
				"url": {
					"raw": "http://localhost:8080/products",
					"protocol": "http",
					"host": [
						"localhost"
					],
					"port": "8080",
					"path": [
						"products"
					]
				}
			},
			"response": []
		},
		{
			"name": "update product",
			"request": {
				"method": "PUT",
				"header": [],
				"body": {
					"mode": "raw",
					"raw": "{\r\n    \r\n    \"title\": \"t2\",\r\n    \"price\": 0.0123,\r\n    \"image\": \"url2new\",\r\n    \"category\":\"cloths2\",\r\n    \"deleted\": false\r\n}",
					"options": {
						"raw": {
							"language": "json"
						}
					}
				},
				"url": {
					"raw": "http://localhost:8080/product/2",
					"protocol": "http",
					"host": [
						"localhost"
					],
					"port": "8080",
					"path": [
						"product",
						"2"
					]
				}
			},
			"response": []
		},
		{
			"name": "Delete product",
			"request": {
				"method": "DELETE",
				"header": [],
				"url": {
					"raw": "http://localhost:8080/product/1",
					"protocol": "http",
					"host": [
						"localhost"
					],
					"port": "8080",
					"path": [
						"product",
						"1"
					]
				}
			},
			"response": []
		},
		{
			"name": "Razorpay",
			"request": {
				"method": "POST",
				"header": [],
				"body": {
					"mode": "raw",
					"raw": "{\r\n    \"email\": \"contact2theshreya@gmail.com\",\r\n    \"phoneNumber\": \"7703965076\",\r\n    \"orderId\": \"t6\",\r\n    \"amount\": 100\r\n}",
					"options": {
						"raw": {
							"language": "json"
						}
					}
				},
				"url": {
					"raw": "http://localhost:8080/payment",
					"protocol": "http",
					"host": [
						"localhost"
					],
					"port": "8080",
					"path": [
						"payment"
					]
				}
			},
			"response": []
		},
		{
			"name": "products",
			"request": {
				"method": "GET",
				"header": [
					{
						"key": "AUTH_TOKEN",
						"value": "eyJhbGciOiJIUzI1NiJ9.eyJ1c2VyX2lkIjoxLCJyb2xlcyI6W10sImVtYWlsIjoiY29udGFjdDJ0aGVzaHJleWFAZ21haWwuY29tIiwiZXhwIjoxNzM5ODA5MDY0LCJpYXQiOjE3MzcyMTcwNjR9.AmpMVf5mvBhBv5VXQj8zXK3oWJm33rP9fqmzcf926aA",
						"type": "text"
					},
					{
						"key": "USER_ID",
						"value": "1",
						"type": "text"
					}
				],
				"url": {
					"raw": "http://localhost:8080/products",
					"protocol": "http",
					"host": [
						"localhost"
					],
					"port": "8080",
					"path": [
						"products"
					]
				}
			},
			"response": []
		}
	]
}